src/__init__.py
src/configure.py
src/main.py
src/watcher.py
pytest_file_watcher-0.2.4.dist-info/LICENSE
pytest_file_watcher-0.2.4.dist-info/METADATA
pytest_file_watcher-0.2.4.dist-info/WHEEL
pytest_file_watcher-0.2.4.dist-info/entry_points.txt
pytest_file_watcher-0.2.4.dist-info/top_level.txt
pytest_file_watcher-0.2.4.dist-info/RECORD
