Metadata-Version: 2.1
Name: pytest-file-watcher
Version: 0.2.4
Summary: Pytest-File-Watcher is a CLI tool that watches for changes in your code and runs pytest on the changed files.
Home-page: https://github.com/deviljin112/Pytest-File-Watcher
Author: Deviljin112
License: MIT
Keywords: python pytest testing testing-tools watch watcher
Requires-Python: >=3.9
License-File: LICENSE
Requires-Dist: PyYAML (==6.0)
Requires-Dist: watchfiles (==0.18.1)
Requires-Dist: typer (==0.7.0)
Requires-Dist: rich (==12.6.0)
Requires-Dist: pytest
